pca_impute/__init__.py
pca_impute/_impute.py
pca_impute-1.0.dist-info/LICENSE
pca_impute-1.0.dist-info/METADATA
pca_impute-1.0.dist-info/WHEEL
pca_impute-1.0.dist-info/top_level.txt
pca_impute-1.0.dist-info/RECORD
